.gitignore
.pre-commit-config.yaml
README.md
customize.py
pyproject.toml
requirements.txt
setup.cfg
setup.py
.github/workflows/CI.template
.github/workflows/CI.yml
.github/workflows/publish.yml
.ipynb_checkpoints/scratchpad-checkpoint.ipynb
advi_jax/__init__.py
advi_jax/_version.py
advi_jax/advi.py
advi_jax/coin_toss.gif
advi_jax/init.py
advi_jax/metrics.py
advi_jax/scratchpad.ipynb
advi_jax/variational_distributions.py
advi_jax.egg-info/PKG-INFO
advi_jax.egg-info/SOURCES.txt
advi_jax.egg-info/dependency_links.txt
advi_jax.egg-info/requires.txt
advi_jax.egg-info/top_level.txt
advi_jax/.ipynb_checkpoints/scratchpad-checkpoint.ipynb
tests/__init__.py
tests/test_imports.py