Metadata-Version: 2.1
Name: advi-jax
Version: 0.0.1
Summary: ADVI library for generelized graphical models
Home-page: https://github.com/patel-zeel/advi_jax
Author: Zeel B Patel
Author-email: patel_zeel@iitgn.ac.in
License: MIT
Platform: UNKNOWN
Requires-Python: >=3.6
